ADMCode/__init__.py
ADMCode/believer_skeptic.py
ADMCode/ddm.py
ADMCode/neural.py
ADMCode/qlearn.py
ADMCode/sdt.py
ADMCode/utils.py
ADMCode/visualize.py
ADMCode/snuz/__init__.py
ADMCode/snuz/ars/__init__.py
ADMCode/snuz/ars/ars.py
ADMCode/snuz/ars/filter.py
ADMCode/snuz/ars/logz.py
ADMCode/snuz/ars/lqr_env.py
ADMCode/snuz/ars/optimizers.py
ADMCode/snuz/ars/policies.py
ADMCode/snuz/ars/run_policy.py
ADMCode/snuz/ars/shared_noise.py
ADMCode/snuz/ars/utils.py
ADMCode/snuz/ppo/__init__.py
ADMCode/snuz/ppo/envs.py
ADMCode/snuz/ppo/models.py
ADMCode/snuz/ppo/run_ppo.py
ADMCode/snuz/ppo/storage.py
ADMCode/snuz/ppo/utils.py
ADMCode/snuz/ppo/agents/__init__.py
ADMCode/snuz/ppo/agents/ppo_gae.py
ADMCode/snuz/ppo/agents/reinforce.py
ADMCode/styles/custom.css
ADMCode-0.5.2.dist-info/METADATA
ADMCode-0.5.2.dist-info/RECORD
ADMCode-0.5.2.dist-info/WHEEL
ADMCode-0.5.2.dist-info/top_level.txt
